mixture_llm/__init__.py
mixture_llm/core.py
mixture_llm/py.typed
mixture_llm-0.1.1.dist-info/licenses/LICENSE
mixture_llm-0.1.1.dist-info/METADATA
mixture_llm-0.1.1.dist-info/WHEEL
mixture_llm-0.1.1.dist-info/top_level.txt
mixture_llm-0.1.1.dist-info/RECORD
