Metadata-Version: 2.4
Name: mixture-llm
Version: 0.1.1
Summary: Lightweight Mixture of Agents pipeline framework.
Author-email: Leonard O'Sullivan <leonard@machine.dev>
License: MIT License
Project-URL: Homepage, https://github.com/leonardosul/mixture-llm
Project-URL: Documentation, https://leonardosul.github.io/mixture-llm/
Project-URL: Issues, https://github.com/leonardosul/mixture-llm/issues
Keywords: llm,moa,mixture-of-agents,prompting,pipelines
Classifier: Development Status :: 3 - Alpha
Classifier: Intended Audience :: Developers
Classifier: License :: OSI Approved :: MIT License
Classifier: Programming Language :: Python :: 3
Classifier: Programming Language :: Python :: 3 :: Only
Classifier: Programming Language :: Python :: 3.10
Classifier: Programming Language :: Python :: 3.11
Classifier: Programming Language :: Python :: 3.12
Classifier: Programming Language :: Python :: 3.13
Classifier: Typing :: Typed
Requires-Python: >=3.10
License-File: LICENSE
Provides-Extra: openai
Requires-Dist: openai>=1.0.0; extra == "openai"
Provides-Extra: litellm
Requires-Dist: litellm>=1.0.0; extra == "litellm"
Provides-Extra: examples
Requires-Dist: openai>=1.0.0; extra == "examples"
Requires-Dist: litellm>=1.0.0; extra == "examples"
Provides-Extra: dev
Requires-Dist: mixture-llm[examples]; extra == "dev"
Requires-Dist: pytest>=8; extra == "dev"
Requires-Dist: pytest-asyncio>=0.24; extra == "dev"
Requires-Dist: ruff>=0.6; extra == "dev"
Requires-Dist: pre-commit>=3.8; extra == "dev"
Requires-Dist: build>=1.2; extra == "dev"
Requires-Dist: twine>=5.1; extra == "dev"
Provides-Extra: docs
Requires-Dist: mkdocs>=1.6; extra == "docs"
Requires-Dist: mkdocs-material>=9.5; extra == "docs"
Requires-Dist: mkdocstrings[python]>=0.25; extra == "docs"
Dynamic: license-file
